nornir_sql/__init__.py
nornir_sql/plugins/inventory/__init__.py
nornir_sql/plugins/inventory/errors.py
nornir_sql/plugins/inventory/sql.py
nornir_sql-0.1.0.dist-info/entry_points.txt
nornir_sql-0.1.0.dist-info/licenses/LICENSE
nornir_sql-0.1.0.dist-info/WHEEL
nornir_sql-0.1.0.dist-info/METADATA
nornir_sql-0.1.0.dist-info/RECORD
