Metadata-Version: 2.4
Name: nornir_sql
Version: 0.1.0
Summary: nornir_sql
Author-email: Viktor Kertesz <vkertesz2@gmail.com>
Requires-Python: >=3.7,<4
Classifier: License :: OSI Approved :: MIT License
Classifier: Operating System :: Microsoft :: Windows
Classifier: Operating System :: POSIX :: Linux
Classifier: Programming Language :: Python :: 3
Classifier: Topic :: Software Development :: Libraries :: Python Modules
License-File: LICENSE
Requires-Dist: nornir >=3,<4
Requires-Dist: sqlalchemy >=2.0
Requires-Dist: black ; extra == "dev"
Requires-Dist: pytest-cov ; extra == "dev"
Requires-Dist: pytest ; extra == "dev"
Requires-Dist: pylint ; extra == "dev"
Requires-Dist: flit>=3.2 ; extra == "dev"
Requires-Dist: invoke ; extra == "dev"
Requires-Dist: toml ; extra == "dev"
Requires-Dist: Sphinx<3.6 ; extra == "dev"
Requires-Dist: sphinx_rtd_theme ; extra == "dev"
Project-URL: Documentation, https://realvitya.github.io/nornir_sql
Project-URL: Source, https://github.com/realvitya/nornir_sql
Provides-Extra: dev
